cdk_fargate_patterns/__init__.py
cdk_fargate_patterns/py.typed
cdk_fargate_patterns/_jsii/__init__.py
cdk_fargate_patterns/_jsii/cdk-fargate-patterns@0.3.101.jsii.tgz
cdk_fargate_patterns-0.3.101.dist-info/LICENSE
cdk_fargate_patterns-0.3.101.dist-info/METADATA
cdk_fargate_patterns-0.3.101.dist-info/WHEEL
cdk_fargate_patterns-0.3.101.dist-info/top_level.txt
cdk_fargate_patterns-0.3.101.dist-info/RECORD
